README.md
setup.py
directed_information/__init__.py
directed_information/compute_DI_MI.py
directed_information/ctwalgorithm.py
directed_information/ctwentropy.py
directed_information/fast_mat_DI.py
directed_information.egg-info/PKG-INFO
directed_information.egg-info/SOURCES.txt
directed_information.egg-info/dependency_links.txt
directed_information.egg-info/not-zip-safe
directed_information.egg-info/requires.txt
directed_information.egg-info/top_level.txt