Metadata-Version: 2.1
Name: directed-information
Version: 0.1
Summary: Universal Estimation of Directed Information
Home-page: https://github.com/elipugh/directed_information
Author: Eli Pugh
Author-email: epugh@stanford.edu
License: MIT
Keywords: universal,directed,information,estimation,mutual
Platform: UNKNOWN
Classifier: Programming Language :: Python :: 3
Classifier: License :: OSI Approved :: MIT License
Classifier: Operating System :: OS Independent
